gocardless_to_csv/gocardless-to-csv.py
gocardless_to_csv-0.5.0.dist-info/LICENSE
gocardless_to_csv-0.5.0.dist-info/WHEEL
gocardless_to_csv-0.5.0.dist-info/METADATA
gocardless_to_csv-0.5.0.dist-info/RECORD
